datemath/__init__.py
datemath/_version.py
datemath/helpers.py
datemath/py.typed
python_datemath-3.0.3.dist-info/LICENSE
python_datemath-3.0.3.dist-info/METADATA
python_datemath-3.0.3.dist-info/WHEEL
python_datemath-3.0.3.dist-info/top_level.txt
python_datemath-3.0.3.dist-info/RECORD
