Metadata-Version: 2.1
Name: python-datemath
Version: 3.0.3
Summary: "A python module to emulate the date math used in SOLR and Elasticsearch"
Home-page: https://github.com/nickmaccarthy/python-datemath
Download-URL: https://github.com/nickmaccarthy/python-datemath/tarball/3.0.3
Author: Nick MacCarthy
Author-email: nickmaccarthy@gmail.com
License: Apache-2.0
Keywords: date math datemath elaticsearch solr
Classifier: Development Status :: 5 - Production/Stable
Classifier: Intended Audience :: Developers
Classifier: Topic :: Software Development :: Build Tools
Classifier: License :: OSI Approved :: Apache Software License
Classifier: Programming Language :: Python :: 3 :: Only
Classifier: Programming Language :: Python :: 3.8
Classifier: Programming Language :: Python :: 3.9
Classifier: Programming Language :: Python :: 3.10
Classifier: Programming Language :: Python :: 3.11
Classifier: Programming Language :: Python :: 3.12
Classifier: Operating System :: OS Independent
Requires-Python: >=3.8
License-File: LICENSE
Requires-Dist: arrow
Provides-Extra: dev
Requires-Dist: check-manifest ; extra == 'dev'
Provides-Extra: test
Requires-Dist: coverage ; extra == 'test'
